huskytools/__init__.py
huskytools/huskylens.py
tests/__init__.py
tests/test_huskylens.py
huskytools-0.2.1.dist-info/LICENSE
huskytools-0.2.1.dist-info/METADATA
huskytools-0.2.1.dist-info/WHEEL
huskytools-0.2.1.dist-info/top_level.txt
huskytools-0.2.1.dist-info/RECORD
