Metadata-Version: 2.1
Name: huskytools
Version: 0.2.1
Summary: Tools for interacting with the HuskyLens AI camera
Home-page: https://github.com/Andreasdahlberg/husky-tools
Author: Andreas Dahlberg
Author-email: andreas.dahlberg90@gmail.com
License: MIT
Project-URL: Bug Reports, https://github.com/Andreasdahlberg/husky-tools/issues
Project-URL: Source, https://github.com/Andreasdahlberg/husky-tools/
Keywords: huskylens face-recognition camera
Classifier: Development Status :: 3 - Alpha
Classifier: License :: OSI Approved :: MIT License
Classifier: Programming Language :: Python :: 3
Requires-Python: >=3.8
License-File: LICENSE
Requires-Dist: pyserial (>=3.4)
